Workbook

Sheet Read me
A1: NESR SCMS: System and Technical Requirements
A2: Team 3. Satellite communication and observation along the sea route in all weather conditions with monitoring of ice conditions.
A4: Structure (NASA SE Handbook SP-2016-6105 Rev2, processes 4.1 and 4.2)
A5: System reqs: 11 requirements stating what stakeholders need from the system, each with a measure of effectiveness (MOE); validated.
A6: Technical reqs: 32 measurable engineering requirements, each with one verification method and a trace to system reqs; verified.
A7: Traceability: matrix of technical (rows) against system (columns) requirements; the bottom rows check coverage.
A8: Verification summary: number of technical requirements per type and verification method (formulas).
A10: Codes
A11: T = Test, A = Analysis, I = Inspection, D = Demonstration. TBR = value proposed, to be confirmed.
A13: Cells to edit
A14: Yellow cells (Status, Notes) are for the team: pick a Status from the list (Draft, Agreed, Baselined, Deleted) and add notes.
A15: Example: set TR-13 Status to 'Agreed' after the Kondor-FKA revisit simulation confirms the 24 h value.

Sheet Stakeholders
A1: Code | B1: Stakeholder | C1: Role in the system | D1: Main concern
A2: SO | B2: Ship operators (master and crew) | C2: Send ship data, receive route updates and warnings | D2: Safe passage through ice, day or night, in any weather
A3: OW | B3: Ship and cargo owners | C3: Receive voyage status and route decisions | D3: Schedule, fuel cost, cargo safety, data confidentiality
A4: LO | B4: Logistics Operators | C4: Plan and follow voyages on the mission dashboard | D4: Predictable ETAs, early warning of delays
A5: PA | B5: Port Authorities | C5: Issue navigation and safety directives, watch traffic | D5: Safety and rule compliance on the whole route
A6: DI | B6: Dispatcher | C6: Approves route changes and sends commands to ships | D6: Clear, trustworthy information
A7: RS | B7: Rescue Services | C7: Receive rescue requests, report resource availability | D7: Fast, accurate distress data
A8: SS | B8: Satellite Systems' Operators | C8: Provide SAR, meteo, relay and navigation services | D8: Requests within capacity, clear interfaces
A9: RG | B9: Regulators (frequency authority, classification society) | C9: Set rules the system must follow | D9: Compliance with radio and marine equipment rules
A10: MS | B10: Maintenance staff (satellite and ship) | C10: Keep terminals and ground equipment working | D10: Fast fault finding and repair

Sheet System reqs
A1: ID | B1: Stakeholder | C1: Requirement | D1: MOE (target) | E1: Validation | F1: Status | G1: Notes
A2: SR-01 | B2: Ship operators | C2: The system shall give the ship's bridge current ice information for the planned route at any time of day or night and in any weather. | D2: Age of ice information on the bridge ≤ 24 h (TBR) for ≥ 95% of voyage time | E2: A | F2: Draft
A3: SR-02 | B3: Ship operators | C3: The system shall warn the ship of ice and storm hazards on its planned route early enough to change course safely. | D3: Warning ≥ 6 h before reaching the hazard zone in ≥ 90% of hazard events | E3: A | F3: Draft
A4: SR-03 | B4: Ship operators | C4: The system shall keep two-way communication between ship and shore available along the whole Northern Sea Route. | D4: ≥ 99% of messages delivered within 5 min anywhere in the service area | E4: D | F4: Draft
A5: SR-04 | B5: Ship and cargo owners, Logistics Operators | C5: The system shall let owners and logistics operators follow the position and ETA of their ships. | D5: Position age ≤ 30 min; ETA error ≤ 6 h at 72 h ahead in ≥ 90% of voyages | E5: A, D | F5: Draft
A6: SR-05 | B6: Port Authorities | C6: The system shall give Port Authorities a live picture of all connected ships on the Northern Sea Route. | D6: 100% of connected ships shown; position age ≤ 30 min | E6: D | F6: Draft
A7: SR-06 | B7: Port Authorities | C7: The system shall deliver Port Authority directives to all affected ships and confirm receipt. | D7: ≥ 99% of affected ships acknowledge within 30 min | E7: D | F7: Draft
A8: SR-07 | B8: Dispatcher | C8: The system shall let the dispatcher decide on route changes quickly, based on alarms that can be trusted. | D8: Decision ≤ 10 min after the alarm in ≥ 90% of operator trials; false alarm ratio ≤ 10% | E8: D, A | F8: Draft
A9: SR-08 | B9: Rescue Services | C9: The system shall pass distress information to Rescue Services quickly and with an accurate position. | D9: Request received ≤ 2 min after the distress alert; position error ≤ 10 m (95%) | E9: T | F9: Draft
A10: SR-09 | B10: Regulators, Port Authorities | C10: The system shall comply with the NSR navigation rules, the Polar Code and the radio and marine equipment regulations that apply to it. | D10: 0 non-conformities at regulatory inspection and in an audit of 100 route recommendations | E10: I | F10: Draft
A11: SR-10 | B11: Ship and cargo owners | C11: The system shall keep each owner's commercial data hidden from other owners and third parties. | D11: 0 unauthorised data accesses in the acceptance penetration test | E11: T | F11: Draft
A12: SR-11 | B12: Maintenance staff | C12: The system shall let maintenance staff find and replace a failed on-board unit quickly. | D12: Fault isolated to one replaceable unit in ≥ 90% of failures; repair ≤ 1 h | E12: D | F12: Draft

Sheet Technical reqs
A1: ID | B1: Type | C1: Requirement | D1: Rationale | E1: Verification | F1: Traces to | G1: TBR | H1: Status | I1: Notes
A2: TR-01 | B2: Functional | C2: The on-board terminal shall send a ship data report (ship ID, GNSS position, course and speed over ground, heading, sensor data per ICD-01) every 15 min by default, configurable from 5 to 60 min. | D2: 15 min keeps displayed positions within the 30 min age limit. | E2: T | F2: SR-04, SR-05, SR-08 | H2: Draft
A3: TR-02 | B3: Functional | C3: The system shall produce ice charts from SAR data giving ice concentration, stage of development and form of ice, at a spatial resolution of 50 m or finer (5 m or finer in the NSR key straits). | D3: WMO ice chart parameters; 50 m matches the RCM ice mode, Kondor-FKA images at up to 1 m. | E3: I | F3: SR-01 | H3: Draft
A4: TR-03 | B4: Functional | C4: The system shall recompute the risk score (0 to 100) of each ship and of each 10 km route segment ahead of it within 15 min of new ice, weather or ship data. | D4: Keeps risk current with the 15 min reporting cycle. | E4: T | F4: SR-02, SR-07 | H4: Draft
A5: TR-04 | B5: Functional | C5: The system shall raise an ALARM when a ship's risk score exceeds 70 (configurable) or its planned route enters a hazard zone within the next 24 h. | D5: Starts the warning and route-change scenario (S2). | E5: T | F5: SR-02, SR-07 | H5: Draft
A6: TR-05 | B6: Functional | C6: Within 5 min of each ALARM, the system shall generate at least 2 alternative routes, each with ETA, distance, fuel estimate and risk score. | D6: The dispatcher needs ranked options to decide within 10 min. | E6: T | F6: SR-02, SR-07 | H6: Draft
A7: TR-06 | B7: Functional | C7: The system shall send a route change to a ship only after a dispatcher has approved it. | D7: A named person stays accountable for every route decision. | E7: T | F7: SR-07, SR-09 | H7: Draft
A8: TR-07 | B8: Functional | C8: The system shall resend each route update or directive that the on-board terminal has not acknowledged up to 3 times at 2 min intervals, then alert the dispatcher. | D8: No silent delivery failure of safety messages. | E8: T | F8: SR-03, SR-06 | H8: Draft
A9: TR-08 | B9: Functional | C9: The system shall keep a tamper-evident log of all datasets, alarms, decisions and sent messages, time-stamped to UTC within ±1 s, for at least 5 years. | D9: Accountability and incident investigation. | E9: I | F9: SR-09 | H9: Draft
A10: TR-09 | B10: Performance | C10: Ship-to-shore and shore-to-ship messaging shall be available ≥ 99.0% of the time over any 30-day period everywhere on the NSR between 66°N and 82°N. | D10: Covers high-latitude legs; verified by coverage and outage simulation. | E10: A | F10: SR-03, SR-05 | H10: Draft
A11: TR-10 | B11: Performance | C11: Route updates and text messages shall reach the addressed ship within 5 min for ≥ 99% of messages. | D11: Keeps the dispatcher-to-ship loop short. | E11: T | F11: SR-03, SR-07 | H11: Draft
A12: TR-11 | B12: Performance | C12: Hazard warnings shall reach affected ships within 10 min of the ALARM for ≥ 95% of warnings, without waiting for dispatcher approval. | D12: Warnings are information, not commands; RCM gives 10–30 min for maritime surveillance. | E12: T | F12: SR-02 | H12: Draft
A13: TR-12 | B13: Performance | C13: Hazard warnings shall be issued at least 6 h before the ship's forecast entry into the hazard zone in ≥ 90% of hazard events. | D13: Ships in ice need hours to re-route or wait for an icebreaker. | E13: A | F13: SR-02 | H13: Draft
A14: TR-13 | B14: Performance | C14: The age of ice information shown on the bridge shall not exceed 24 h (TBR) for ≥ 95% of voyage time. | D14: Key TPM: SAR revisit time plus processing and delivery time. | E14: A | F14: SR-01 | G14: TBR | H14: Draft
A15: TR-14 | B15: Performance | C15: The system shall publish an ice chart within 60 min of receiving a SAR product. | D15: Ice drifts tens of kilometres per day; processing adds to information age. | E15: T | F15: SR-01 | H15: Draft
A16: TR-15 | B16: Performance | C16: The ALARM function shall detect ≥ 95% of hazard events with a false alarm ratio of no more than 10% on the validation dataset. | D16: Balances safety against dispatcher trust in alarms. | E16: A | F16: SR-02, SR-07 | H16: Draft
A17: TR-16 | B17: Performance | C17: The ETA forecast error shall not exceed 6 h at 72 h ahead in ≥ 90% of voyages. | D17: Back-tested on recorded 2024–2025 NSR voyages. | E17: A | F17: SR-04 | H17: Draft
A18: TR-17 | B18: Performance | C18: Ship positions shown on dashboards shall be no older than 30 min. | D18: Directly measures SR-04 and SR-05. | E18: T | F18: SR-04, SR-05 | H18: Draft
A19: TR-18 | B19: Performance | C19: Port Authority directives shall be acknowledged by ≥ 99% of affected ships within 30 min of release. | D19: Directly measures SR-06. | E19: T | F19: SR-06 | H19: Draft
A20: TR-19 | B20: Performance | C20: The system shall send a rescue request with ship ID, GNSS position (error ≤ 10 m, 95%), time and persons on board to Rescue Services within 2 min of receiving a distress alert. | D20: Implements the emergency scenario (S6). | E20: T | F20: SR-08 | H20: Draft
A21: TR-20 | B21: Performance | C21: The system shall track at least 500 ships at once and serve at least 50 concurrent operator sessions while meeting all latency requirements. | D21: Margin for NSR traffic growth (37.8 Mt of cargo in 2024). | E21: T | F21: SR-05 | H21: Draft
A22: TR-21 | B22: Interface | C22: The system shall receive SAR products (GeoTIFF, ICD-02) and meteorological data (WMO GRIB2, ICD-03) from the satellite operators' ground segments over secure terrestrial links of at least 100 Mbit/s (TBR). | D22: SAR volumes are too large for the low-rate satellite relay. | E22: T | F22: SR-01, SR-02 | G22: TBR | H22: Draft
A23: TR-22 | B23: Environmental | C23: The on-board antenna unit shall operate at air temperatures from −40 °C to +55 °C. | D23: IEC 60945 exposed-equipment conditions, extended to Arctic winter. | E23: T | F23: SR-03 | H23: Draft
A24: TR-23 | B24: Reliability and maintainability | C24: The ground platform shall have an operational availability of at least 99.5% per year, excluding no more than 8 h of planned maintenance. | D24: Supports the 99.0% end-to-end messaging availability. | E24: A | F24: SR-03, SR-05 | H24: Draft
A25: TR-24 | B25: Reliability and maintainability | C25: The on-board terminal shall have a mean time between failures of at least 20 000 h. | D25: About one failure in 2.3 years of continuous use. | E25: A | F25: SR-11 | H25: Draft
A26: TR-25 | B26: Reliability and maintainability | C26: Built-in test shall isolate at least 90% of on-board terminal failures to one line-replaceable unit that ship staff can replace within 1 h using on-board spares. | D26: Ships may be weeks away from a port with service. | E26: D | F26: SR-11 | H26: Draft
A27: TR-26 | B27: Safety | C27: The system shall mark ice information older than 48 h as DEGRADED on all displays. | D27: Stale ice data shown as current is a navigation hazard. | E27: T | F27: SR-01 | H27: Draft
A28: TR-27 | B28: Security | C28: The system shall give each user access only to the data allowed by their role; owners shall see only their own ships. | D28: Directly implements SR-10. | E28: T | F28: SR-10 | H28: Draft
A29: TR-28 | B29: Security | C29: All data links shall be encrypted with a nationally approved algorithm using keys of at least 256 bit. | D29: Ship positions and cargo data are commercially sensitive. | E29: I | F29: SR-10 | H29: Draft
A30: TR-29 | B30: Regulatory | C30: Route recommendations shall comply with the current NSR navigation rules and include the Polar Code Chapter 11 ice information (current extent and type of ice near the route). | D30: Mandatory for ships on the NSR; Polar Code 11.3.3. | E30: I | F30: SR-09, SR-01 | H30: Draft
A31: TR-30 | B31: Regulatory | C31: All system radio links shall operate only in the frequency bands and power limits licensed by the national frequency authority. | D31: ITU Radio Regulations and national law. | E31: I | F31: SR-09 | H31: Draft
A32: TR-31 | B32: Regulatory | C32: The on-board terminal shall hold a type approval certificate, based on IEC 60945 tests, from the Russian Maritime Register of Shipping or the flag state's classification society. | D32: Required for installation on classed ships. | E32: I | F32: SR-09 | H32: Draft
A33: TR-32 | B33: Human factors | C33: A dispatcher shall be able to review an ALARM and approve or reject a route change within 10 min, with all inputs on one screen, in ≥ 90% of trials. | D33: Directly measures SR-07. | E33: D | F33: SR-07 | H33: Draft

Sheet Traceability
A1: TR \ SR | B1: SR-01 | C1: SR-02 | D1: SR-03 | E1: SR-04 | F1: SR-05 | G1: SR-06 | H1: SR-07 | I1: SR-08 | J1: SR-09 | K1: SR-10 | L1: SR-11 | M1: Traces (count)
A2: TR-01 | E2: X | F2: X | I2: X | M2: =COUNTIF(B2:L2,"X") -> 3
A3: TR-02 | B3: X | M3: =COUNTIF(B3:L3,"X") -> 1
A4: TR-03 | C4: X | H4: X | M4: =COUNTIF(B4:L4,"X") -> 2
A5: TR-04 | C5: X | H5: X | M5: =COUNTIF(B5:L5,"X") -> 2
A6: TR-05 | C6: X | H6: X | M6: =COUNTIF(B6:L6,"X") -> 2
A7: TR-06 | H7: X | J7: X | M7: =COUNTIF(B7:L7,"X") -> 2
A8: TR-07 | D8: X | G8: X | M8: =COUNTIF(B8:L8,"X") -> 2
A9: TR-08 | J9: X | M9: =COUNTIF(B9:L9,"X") -> 1
A10: TR-09 | D10: X | F10: X | M10: =COUNTIF(B10:L10,"X") -> 2
A11: TR-10 | D11: X | H11: X | M11: =COUNTIF(B11:L11,"X") -> 2
A12: TR-11 | C12: X | M12: =COUNTIF(B12:L12,"X") -> 1
A13: TR-12 | C13: X | M13: =COUNTIF(B13:L13,"X") -> 1
A14: TR-13 | B14: X | M14: =COUNTIF(B14:L14,"X") -> 1
A15: TR-14 | B15: X | M15: =COUNTIF(B15:L15,"X") -> 1
A16: TR-15 | C16: X | H16: X | M16: =COUNTIF(B16:L16,"X") -> 2
A17: TR-16 | E17: X | M17: =COUNTIF(B17:L17,"X") -> 1
A18: TR-17 | E18: X | F18: X | M18: =COUNTIF(B18:L18,"X") -> 2
A19: TR-18 | G19: X | M19: =COUNTIF(B19:L19,"X") -> 1
A20: TR-19 | I20: X | M20: =COUNTIF(B20:L20,"X") -> 1
A21: TR-20 | F21: X | M21: =COUNTIF(B21:L21,"X") -> 1
A22: TR-21 | B22: X | C22: X | M22: =COUNTIF(B22:L22,"X") -> 2
A23: TR-22 | D23: X | M23: =COUNTIF(B23:L23,"X") -> 1
A24: TR-23 | D24: X | F24: X | M24: =COUNTIF(B24:L24,"X") -> 2
A25: TR-24 | L25: X | M25: =COUNTIF(B25:L25,"X") -> 1
A26: TR-25 | L26: X | M26: =COUNTIF(B26:L26,"X") -> 1
A27: TR-26 | B27: X | M27: =COUNTIF(B27:L27,"X") -> 1
A28: TR-27 | K28: X | M28: =COUNTIF(B28:L28,"X") -> 1
A29: TR-28 | K29: X | M29: =COUNTIF(B29:L29,"X") -> 1
A30: TR-29 | B30: X | J30: X | M30: =COUNTIF(B30:L30,"X") -> 2
A31: TR-30 | J31: X | M31: =COUNTIF(B31:L31,"X") -> 1
A32: TR-31 | J32: X | M32: =COUNTIF(B32:L32,"X") -> 1
A33: TR-32 | H33: X | M33: =COUNTIF(B33:L33,"X") -> 1
A34: Covered by (count) | B34: =COUNTIF(B2:B33,"X") -> 6 | C34: =COUNTIF(C2:C33,"X") -> 7 | D34: =COUNTIF(D2:D33,"X") -> 5 | E34: =COUNTIF(E2:E33,"X") -> 3 | F34: =COUNTIF(F2:F33,"X") -> 5 | G34: =COUNTIF(G2:G33,"X") -> 2 | H34: =COUNTIF(H2:H33,"X") -> 7 | I34: =COUNTIF(I2:I33,"X") -> 2 | ... L34: =COUNTIF(L2:L33,"X") -> 2
A35: Uncovered SR | B35: =COUNTIF(B34:L34,0) -> 0
A36: Untraced TR | B36: =COUNTIF(M2:M33,0) -> 0

Sheet Verification summary
A1: Type | B1: Test (T) | C1: Analysis (A) | D1: Inspection (I) | E1: Demonstration (D) | F1: Total
A2: Functional | B2: =COUNTIFS('Technical reqs'!$B$2:$B$33,$A2,'Technical reqs'!$E$2:$E$33,"T") -> 6 | C2: =COUNTIFS('Technical reqs'!$B$2:$B$33,$A2,'Technical reqs'!$E$2:$E$33,"A") -> 0 | D2: =COUNTIFS('Technical reqs'!$B$2:$B$33,$A2,'Technical reqs'!$E$2:$E$33,"I") -> 2 | E2: =COUNTIFS('Technical reqs'!$B$2:$B$33,$A2,'Technical reqs'!$E$2:$E$33,"D") -> 0 | F2: =SUM(B2:E2) -> 8
A3: Performance | B3: =COUNTIFS('Technical reqs'!$B$2:$B$33,$A3,'Technical reqs'!$E$2:$E$33,"T") -> 7 | C3: =COUNTIFS('Technical reqs'!$B$2:$B$33,$A3,'Technical reqs'!$E$2:$E$33,"A") -> 5 | D3: =COUNTIFS('Technical reqs'!$B$2:$B$33,$A3,'Technical reqs'!$E$2:$E$33,"I") -> 0 | E3: =COUNTIFS('Technical reqs'!$B$2:$B$33,$A3,'Technical reqs'!$E$2:$E$33,"D") -> 0 | F3: =SUM(B3:E3) -> 12
A4: Interface | B4: =COUNTIFS('Technical reqs'!$B$2:$B$33,$A4,'Technical reqs'!$E$2:$E$33,"T") -> 1 | C4: =COUNTIFS('Technical reqs'!$B$2:$B$33,$A4,'Technical reqs'!$E$2:$E$33,"A") -> 0 | D4: =COUNTIFS('Technical reqs'!$B$2:$B$33,$A4,'Technical reqs'!$E$2:$E$33,"I") -> 0 | E4: =COUNTIFS('Technical reqs'!$B$2:$B$33,$A4,'Technical reqs'!$E$2:$E$33,"D") -> 0 | F4: =SUM(B4:E4) -> 1
A5: Environmental | B5: =COUNTIFS('Technical reqs'!$B$2:$B$33,$A5,'Technical reqs'!$E$2:$E$33,"T") -> 1 | C5: =COUNTIFS('Technical reqs'!$B$2:$B$33,$A5,'Technical reqs'!$E$2:$E$33,"A") -> 0 | D5: =COUNTIFS('Technical reqs'!$B$2:$B$33,$A5,'Technical reqs'!$E$2:$E$33,"I") -> 0 | E5: =COUNTIFS('Technical reqs'!$B$2:$B$33,$A5,'Technical reqs'!$E$2:$E$33,"D") -> 0 | F5: =SUM(B5:E5) -> 1
A6: Reliability and maintainability | B6: =COUNTIFS('Technical reqs'!$B$2:$B$33,$A6,'Technical reqs'!$E$2:$E$33,"T") -> 0 | C6: =COUNTIFS('Technical reqs'!$B$2:$B$33,$A6,'Technical reqs'!$E$2:$E$33,"A") -> 2 | D6: =COUNTIFS('Technical reqs'!$B$2:$B$33,$A6,'Technical reqs'!$E$2:$E$33,"I") -> 0 | E6: =COUNTIFS('Technical reqs'!$B$2:$B$33,$A6,'Technical reqs'!$E$2:$E$33,"D") -> 1 | F6: =SUM(B6:E6) -> 3
A7: Safety | B7: =COUNTIFS('Technical reqs'!$B$2:$B$33,$A7,'Technical reqs'!$E$2:$E$33,"T") -> 1 | C7: =COUNTIFS('Technical reqs'!$B$2:$B$33,$A7,'Technical reqs'!$E$2:$E$33,"A") -> 0 | D7: =COUNTIFS('Technical reqs'!$B$2:$B$33,$A7,'Technical reqs'!$E$2:$E$33,"I") -> 0 | E7: =COUNTIFS('Technical reqs'!$B$2:$B$33,$A7,'Technical reqs'!$E$2:$E$33,"D") -> 0 | F7: =SUM(B7:E7) -> 1
A8: Security | B8: =COUNTIFS('Technical reqs'!$B$2:$B$33,$A8,'Technical reqs'!$E$2:$E$33,"T") -> 1 | C8: =COUNTIFS('Technical reqs'!$B$2:$B$33,$A8,'Technical reqs'!$E$2:$E$33,"A") -> 0 | D8: =COUNTIFS('Technical reqs'!$B$2:$B$33,$A8,'Technical reqs'!$E$2:$E$33,"I") -> 1 | E8: =COUNTIFS('Technical reqs'!$B$2:$B$33,$A8,'Technical reqs'!$E$2:$E$33,"D") -> 0 | F8: =SUM(B8:E8) -> 2
A9: Regulatory | B9: =COUNTIFS('Technical reqs'!$B$2:$B$33,$A9,'Technical reqs'!$E$2:$E$33,"T") -> 0 | C9: =COUNTIFS('Technical reqs'!$B$2:$B$33,$A9,'Technical reqs'!$E$2:$E$33,"A") -> 0 | D9: =COUNTIFS('Technical reqs'!$B$2:$B$33,$A9,'Technical reqs'!$E$2:$E$33,"I") -> 3 | E9: =COUNTIFS('Technical reqs'!$B$2:$B$33,$A9,'Technical reqs'!$E$2:$E$33,"D") -> 0 | F9: =SUM(B9:E9) -> 3
A10: Human factors | B10: =COUNTIFS('Technical reqs'!$B$2:$B$33,$A10,'Technical reqs'!$E$2:$E$33,"T") -> 0 | C10: =COUNTIFS('Technical reqs'!$B$2:$B$33,$A10,'Technical reqs'!$E$2:$E$33,"A") -> 0 | D10: =COUNTIFS('Technical reqs'!$B$2:$B$33,$A10,'Technical reqs'!$E$2:$E$33,"I") -> 0 | E10: =COUNTIFS('Technical reqs'!$B$2:$B$33,$A10,'Technical reqs'!$E$2:$E$33,"D") -> 1 | F10: =SUM(B10:E10) -> 1
A11: Total | B11: =SUM(B2:B10) -> 17 | C11: =SUM(C2:C10) -> 7 | D11: =SUM(D2:D10) -> 6 | E11: =SUM(E2:E10) -> 2 | F11: =SUM(F2:F10) -> 32

Sheet Open items
A1: Kind | B1: Affects | C1: Item | D1: Status | E1: Owner
A2: Value | B2: SR-01, TR-13 | C2: Ice information age of 24 h: confirm with a Kondor-FKA revisit simulation over the NSR. | D2: Open
A3: Value | B3: TR-21 | C3: Ground link capacity of 100 Mbit/s: size from the daily SAR and meteo data volume. | D3: Open
A4: Value | B4: Scope | C4: Service area bounds 66°N–82°N, Kara Gates to Bering Strait: check against the official NSR water area. | D4: Open
A5: Assumption | B5: Boundary | C5: Data Analysis Centers' models are inside the system boundary; the SAB currently shows them as an external actor. | D5: Open
A6: Assumption | B6: TR-21 | C6: SAR and meteo data reach the system through the satellite operators' ground segments, not through Gonets/Sfera. | D6: Open
A7: Assumption | B7: Interfaces | C7: ICD-01 to ICD-06 are written by the interface engineer and baselined with the requirements. | D7: Open
A8: Assumption | B8: Benchmarks | C8: RCM benchmarks (daily 50 m ice, 10–30 min maritime latency) accepted as realistic for the NSR. | D8: Open
